{
  "C:\\" : {
    "Folder1" : {
      "plan.txt" : "1. Use money to buy america. \n 2. Sell america to russia. \n 3. Use all of the money to live on mars. \n 4. Start an interstellar war.",
      "contact.txt" : "Personal email : president@gmail.com \n Phone number : 123",
      "homework.img" : "--- Unable to view on this device ---"
    },
    "Folder2" : {
      "minecraft.png" : "o-|===>",
      "passcode.enc" : "Admin code : 3987 for the next task...",
      "balance.txt" : "My moneyyy : 1,000,000,000,000 dogecoin"
    },
    "Folder3" : {
      "encrypted.txt" : "Encrypted password: admin123",
      "skateboard.jpg" : "o---o",
      "targets.txt" : "1. Doge \n 2. The beans guy \n 3. America \n 4. DoctorRiptide"
    }
  }
}
